{
  "bytes": {
    "long": 13000
  },
  "custom_primitives": {
    "icmptypeipv4": "0",
    "ipttlmax": "64",
    "tenantdestipv4": "0.0.0.0",
    "tenantdestport": "0",
    "tenantprotocol": "0",
    "tenantsourceipv4": "0.0.0.0",
    "tenantsourceport": "0",
    "virtualobsid": "95ce4dc0-c14d-428c-8062-8f947e5bc721",
    "vmuuid": ""
  },
  "flows": null,
  "ip_dst": "11.0.9.3",
  "ip_proto": "tcp",
  "ip_src": "11.0.9.2",
  "label": {
    "nkey": "unknown",
    "pkey": "unknown"
  },
  "mac_dst": "00:00:00:00:00:00",
  "mac_src": "00:00:00:00:00:00",
  "packets": {
    "long": 250
  },
  "peer_ip_src": "::ffff:192.168.100.2",
  "port_dst": 2379,
  "port_src": 43332,
  "sampling_direction": "i",
  "stamp_inserted": {
    "string": "1719325320"
  },
  "stamp_updated": {
    "string": "1719325380"
  },
  "tcp_flags": [
    "ACK"
  ],
  "vxlan": 0,
  "writer_id": "taarole8_rocky"
}